mitchallen/__init__.py
mitchallen/coin/__init__.py
mitchallen_coin-1.0.15.dist-info/METADATA
mitchallen_coin-1.0.15.dist-info/WHEEL
mitchallen_coin-1.0.15.dist-info/licenses/LICENSE
mitchallen_coin-1.0.15.dist-info/RECORD
