Metadata-Version: 2.4
Name: mitchallen-coin
Version: 1.0.15
Summary: A simple, lightweight Python package for coin flip simulations, perfect for 50/50 decisions, games, and probabilistic applications
Project-URL: Homepage, https://github.com/mitchallen/python-coin-flip
Project-URL: Repository, https://github.com/mitchallen/python-coin-flip
Project-URL: Issues, https://github.com/mitchallen/python-coin-flip/issues
Author: Mitch Allen
License: MIT
License-File: LICENSE
Keywords: coin,flip,generator,random,random-number
Classifier: Development Status :: 4 - Beta
Classifier: Intended Audience :: Developers
Classifier: License :: OSI Approved :: MIT License
Classifier: Programming Language :: Python :: 3
Classifier: Programming Language :: Python :: 3.12
Classifier: Programming Language :: Python :: 3.13
Classifier: Topic :: Software Development :: Libraries :: Python Modules
Classifier: Topic :: Utilities
Requires-Python: >=3.12
